vllm_logits/__init__.py
vllm_logits/concurrent.py
vllm_logits/data.py
vllm_logits/file.py
vllm_logits/io.py
vllm_logits/list.py
vllm_logits/logging.py
vllm_logits/metrics.py
vllm_logits/misc.py
vllm_logits/ml.py
vllm_logits/pattern.py
vllm_logits/pg.py
vllm_logits/slack.py
vllm_logits/socket.py
vllm_logits/sql.py
vllm_logits/string.py
vllm_logits/tensor.py
vllm_logits/testing.py
vllm_logits/time.py
vllm_logits/wandb.py
vllm_logits-0.1.dist-info/METADATA
vllm_logits-0.1.dist-info/WHEEL
vllm_logits-0.1.dist-info/licenses/LICENSE
vllm_logits-0.1.dist-info/RECORD
