Metadata-Version: 2.4
Name: vllm_logits
Version: 0.1
Summary: A collection of useful util functions
Project-URL: Homepage, https://github.com/hyukkyukang/python_utils
Project-URL: Bug Tracker, https://github.com/hyukkyukang/python_utils/issues
Author-email: Hyukkyu Kang <hyukkyukang@gmail.com>
License-File: LICENSE
Classifier: License :: OSI Approved :: MIT License
Classifier: Operating System :: OS Independent
Classifier: Programming Language :: Python :: 3
Requires-Python: >=3.10
Requires-Dist: dacite
Requires-Dist: nltk
Requires-Dist: numpy
Requires-Dist: omegaconf
Requires-Dist: pglast
Requires-Dist: psycopg[binary,pool]
Requires-Dist: python-dotenv
Requires-Dist: slack-sdk
Requires-Dist: sqlfluff
Requires-Dist: torch
Requires-Dist: ujson
Requires-Dist: wandb
